sipametrics/__init__.py
sipametrics/constants.py
sipametrics/internal/clients.py
sipametrics/internal/endpoints.py
sipametrics/internal/markers.py
sipametrics/internal/permissions.py
sipametrics/loaders.py
sipametrics/models/base.py
sipametrics/models/custom_benchmarks.py
sipametrics/models/direct_alpha.py
sipametrics/models/indices_catalogue.py
sipametrics/models/metrics.py
sipametrics/models/metrics_catalogue.py
sipametrics/models/pe_comparables.py
sipametrics/models/permissions.py
sipametrics/models/pi_comparables.py
sipametrics/models/taxonomies.py
sipametrics/models/term_structures.py
sipametrics/services.py
sipametrics/utilities.py
sipametrics-0.2.5.dist-info/LICENSE
sipametrics-0.2.5.dist-info/METADATA
sipametrics-0.2.5.dist-info/WHEEL
sipametrics-0.2.5.dist-info/RECORD
