Metadata-Version: 2.3
Name: sipametrics
Version: 0.2.5
Summary: Scientific Infra & Private Assets
License: Apache-2.0
Author: SIPA
Author-email: support@sipametrics.com
Requires-Python: >=3.10,<4.0
Classifier: License :: OSI Approved :: Apache Software License
Classifier: Programming Language :: Python :: 3
Classifier: Programming Language :: Python :: 3.10
Classifier: Programming Language :: Python :: 3.11
Classifier: Programming Language :: Python :: 3.12
Classifier: Programming Language :: Python :: 3.13
Requires-Dist: aiohttp
Requires-Dist: pandas
Requires-Dist: pydantic
Requires-Dist: python-dateutil
